{
    "os": "Linux-5.4.0-173-generic-x86_64-with-glibc2.29",
    "python": "3.8.10",
    "heartbeatAt": "2024-03-26T10:20:35.130036",
    "startedAt": "2024-03-26T10:20:34.302563",
    "docker": null,
    "cuda": null,
    "args": [],
    "state": "running",
    "program": "main.py",
    "codePathLocal": "main.py",
    "codePath": "main.py",
    "host": "dgx1",
    "username": "rizwank",
    "executable": "/raid/home/rizwank/courses/DLCV/Project/env/bin/python3",
    "cpu_count": 40,
    "cpu_count_logical": 40,
    "cpu_freq": {
        "current": 2930.6587,
        "min": 1200.0,
        "max": 3600.0
    },
    "cpu_freq_per_core": [
        {
            "current": 2744.465,
            "min": 1200.0,
            "max": 3600.0
        },
        {
            "current": 3279.741,
            "min": 1200.0,
            "max": 3600.0
        },
        {
            "current": 2746.213,
            "min": 1200.0,
            "max": 3600.0
        },
        {
            "current": 2734.763,
            "min": 1200.0,
            "max": 3600.0
        },
        {
            "current": 2722.071,
            "min": 1200.0,
            "max": 3600.0
        },
        {
            "current": 2873.736,
            "min": 1200.0,
            "max": 3600.0
        },
        {
            "current": 2707.494,
            "min": 1200.0,
            "max": 3600.0
        },
        {
            "current": 2694.179,
            "min": 1200.0,
            "max": 3600.0
        },
        {
            "current": 2693.58,
            "min": 1200.0,
            "max": 3600.0
        },
        {
            "current": 3267.429,
            "min": 1200.0,
            "max": 3600.0
        },
        {
            "current": 3278.368,
            "min": 1200.0,
            "max": 3600.0
        },
        {
            "current": 3278.361,
            "min": 1200.0,
            "max": 3600.0
        },
        {
            "current": 2906.698,
            "min": 1200.0,
            "max": 3600.0
        },
        {
            "current": 2694.591,
            "min": 1200.0,
            "max": 3600.0
        },
        {
            "current": 2703.238,
            "min": 1200.0,
            "max": 3600.0
        },
        {
            "current": 2714.736,
            "min": 1200.0,
            "max": 3600.0
        },
        {
            "current": 2698.929,
            "min": 1200.0,
            "max": 3600.0
        },
        {
            "current": 2700.537,
            "min": 1200.0,
            "max": 3600.0
        },
        {
            "current": 2705.449,
            "min": 1200.0,
            "max": 3600.0
        },
        {
            "current": 2703.716,
            "min": 1200.0,
            "max": 3600.0
        },
        {
            "current": 3146.473,
            "min": 1200.0,
            "max": 3600.0
        },
        {
            "current": 3233.602,
            "min": 1200.0,
            "max": 3600.0
        },
        {
            "current": 3119.412,
            "min": 1200.0,
            "max": 3600.0
        },
        {
            "current": 2969.907,
            "min": 1200.0,
            "max": 3600.0
        },
        {
            "current": 2987.421,
            "min": 1200.0,
            "max": 3600.0
        },
        {
            "current": 2934.979,
            "min": 1200.0,
            "max": 3600.0
        },
        {
            "current": 2789.172,
            "min": 1200.0,
            "max": 3600.0
        },
        {
            "current": 3269.847,
            "min": 1200.0,
            "max": 3600.0
        },
        {
            "current": 2740.818,
            "min": 1200.0,
            "max": 3600.0
        },
        {
            "current": 3141.656,
            "min": 1200.0,
            "max": 3600.0
        },
        {
            "current": 3220.86,
            "min": 1200.0,
            "max": 3600.0
        },
        {
            "current": 2782.763,
            "min": 1200.0,
            "max": 3600.0
        },
        {
            "current": 2912.73,
            "min": 1200.0,
            "max": 3600.0
        },
        {
            "current": 2738.569,
            "min": 1200.0,
            "max": 3600.0
        },
        {
            "current": 3044.102,
            "min": 1200.0,
            "max": 3600.0
        },
        {
            "current": 2784.348,
            "min": 1200.0,
            "max": 3600.0
        },
        {
            "current": 2883.927,
            "min": 1200.0,
            "max": 3600.0
        },
        {
            "current": 2866.677,
            "min": 1200.0,
            "max": 3600.0
        },
        {
            "current": 2749.528,
            "min": 1200.0,
            "max": 3600.0
        },
        {
            "current": 3274.231,
            "min": 1200.0,
            "max": 3600.0
        }
    ],
    "disk": {
        "/": {
            "total": 438.0733413696289,
            "used": 235.4213523864746
        }
    },
    "gpu": "Tesla V100-SXM2-32GB",
    "gpu_count": 8,
    "gpu_devices": [
        {
            "name": "Tesla V100-SXM2-32GB",
            "memory_total": 34359738368
        },
        {
            "name": "Tesla V100-SXM2-32GB",
            "memory_total": 34359738368
        },
        {
            "name": "Tesla V100-SXM2-32GB",
            "memory_total": 34359738368
        },
        {
            "name": "Tesla V100-SXM2-32GB",
            "memory_total": 34359738368
        },
        {
            "name": "Tesla V100-SXM2-32GB",
            "memory_total": 34359738368
        },
        {
            "name": "Tesla V100-SXM2-32GB",
            "memory_total": 34359738368
        },
        {
            "name": "Tesla V100-SXM2-32GB",
            "memory_total": 34359738368
        },
        {
            "name": "Tesla V100-SXM2-32GB",
            "memory_total": 34359738368
        }
    ],
    "memory": {
        "total": 503.77756118774414
    }
}
